carveman/Controller.py
carveman/__init__.py
carveman/__main__.py
carveman/carver/CarverBase.py
carveman/carver/ImageCarver.py
carveman/carver/PDFCarver.py
carveman/carver/__init__.py
carveman-0.2.0.dist-info/LICENSE.md
carveman-0.2.0.dist-info/METADATA
carveman-0.2.0.dist-info/WHEEL
carveman-0.2.0.dist-info/entry_points.txt
carveman-0.2.0.dist-info/top_level.txt
carveman-0.2.0.dist-info/RECORD
