Metadata-Version: 2.1
Name: carveman
Version: 0.2.0
Summary: File carving for pictures, documents and other files based on it's file signatures
Home-page: https://github.com/5f0ne/carveman
Author: 5f0
License: MIT
Classifier: Operating System :: OS Independent 
Classifier: Programming Language :: Python :: 3 
Classifier: License :: OSI Approved :: MIT License 
License-File: LICENSE.md
Requires-Dist: hash-calc
